{
    "GlobalConstants": "Core",
    "Object": "Core",
    "Script": "Core",
    "Image": "Core",
    "WeakRef": "Core",
    "Reference": "Core",
    "Resource": "Core",
    "InputEventMouseButton": "Input",
    "InputEventMouse": "Input",
    "InputEventKey": "Core",
    "InputEvent": "Core",
    "InputEventWithModifiers": "Core",
    "InputEventJoypadButton": "Input",
    "InputEventMouseMotion": "Input",
    "InputEventJoypadMotion": "Input",
    "InputEventScreenDrag": "Input",
    "InputEventScreenTouch": "Input",
    "InputEventMagnifyGesture": "Input",
    "InputEventGesture": "Input",
    "InputEventPanGesture": "Input",
    "FuncRef": "Core",
    "StreamPeer": "Network",
    "InputEventAction": "Input",
    "PacketPeer": "Core",
    "TCP_Server": "Network",
    "StreamPeerBuffer": "Network",
    "StreamPeerTCP": "Network",
    "PacketPeerStream": "Network",
    "StreamPeerSSL": "Network",
    "IP": "Network",
    "PacketPeerUDP": "Network",
    "MultiplayerAPI": "Core",
    "NetworkedMultiplayerPeer": "Core",
    "_File": "Core",
    "TriangleMesh": "Core",
    "ResourceInteractiveLoader": "Core",
    "PHashTranslation": "Core",
    "UndoRedo": "Editor",
    "MainLoop": "Core",
    "Translation": "Core",
    "HTTPClient": "Network",
    "_Semaphore": "Core",
    "XMLParser": "Core",
    "_Directory": "Core",
    "_Thread": "Core",
    "_Mutex": "Core",
    "PackedDataContainer": "Core",
    "PCKPacker": "Core",
    "AStar": "Core",
    "ConfigFile": "Core",
    "PackedDataContainerRef": "Core",
    "JSONParseResult": "Core",
    "_Geometry": "Core",
    "EncodedObjectAsID": "Core",
    "IP_Unix": "Network",
    "_ResourceLoader": "Core",
    "_ResourceSaver": "Core",
    "_OS": "Core",
    "_Engine": "Core",
    "_Marshalls": "Core",
    "_ClassDB": "Core",
    "_JSON": "Core",
    "ProjectSettings": "Core",
    "InputMap": "Core",
    "TranslationServer": "Core",
    "Performance": "Core",
    "VisualServer": "Graphics",
    "Input": "Core",
    "InputDefault": "Core",
    "AudioServer": "Audio",
    "ARVRServer": "ArVr",
    "PhysicsServer": "Physics",
    "Node2D": "Core",
    "CanvasModulate": "Core",
    "ResourcePreloader": "Core",
    "Control": "Ui",
    "ButtonGroup": "Ui",
    "Node": "Core",
    "InstancePlaceholder": "Core",
    "Viewport": "Core",
    "World": "Core",
    "World2D": "Core",
    "ViewportTexture": "Core",
    "Texture": "Core",
    "HTTPRequest": "Network",
    "Timer": "Core",
    "CanvasItem": "Core",
    "CanvasLayer": "Core",
    "AudioStreamRandomPitch": "Audio",
    "AudioEffectEQ": "Audio",
    "AudioStreamPlayback": "Audio",
    "AudioEffectFilter": "Audio",
    "AudioBusLayout": "Audio",
    "AudioEffectAmplify": "Audio",
    "AudioStream": "Audio",
    "AudioEffect": "Audio",
    "AudioEffectHighPassFilter": "Audio",
    "AudioEffectNotchFilter": "Audio",
    "AudioEffectBandLimitFilter": "Audio",
    "AudioEffectLowShelfFilter": "Audio",
    "AudioEffectEQ21": "Audio",
    "AudioEffectDistortion": "Audio",
    "AudioEffectHighShelfFilter": "Audio",
    "AudioEffectEQ6": "Audio",
    "AudioEffectEQ10": "Audio",
    "AudioEffectReverb": "Audio",
    "AudioEffectLowPassFilter": "Audio",
    "AudioEffectBandPassFilter": "Audio",
    "AudioEffectChorus": "Audio",
    "AudioEffectPanner": "Audio",
    "AudioEffectStereoEnhance": "Audio",
    "AudioEffectDelay": "Audio",
    "AudioEffectCompressor": "Audio",
    "AudioEffectPitchShift": "Audio",
    "AudioEffectLimiter": "Audio",
    "AudioEffectPhaser": "Audio",
    "Physics2DDirectBodyState": "Physics",
    "Physics2DDirectSpaceState": "Physics",
    "Physics2DTestMotionResult": "Physics",
    "Physics2DShapeQueryParameters": "Physics",
    "Physics2DShapeQueryResult": "Physics",
    "PhysicsShapeQueryResult": "Physics",
    "PhysicsDirectBodyState": "Physics",
    "PhysicsDirectSpaceState": "Physics",
    "PhysicsShapeQueryParameters": "Physics",
    "Physics2DServer": "Physics",
    "ARVRInterface": "ArVr",
    "ARVRPositionalTracker": "ArVr",
    "ScrollBar": "Ui",
    "ProgressBar": "Ui",
    "VScrollBar": "Ui",
    "HScrollBar": "Ui",
    "Slider": "Ui",
    "Label": "Ui",
    "Range": "Ui",
    "Button": "Ui",
    "Theme": "Ui",
    "BaseButton": "Ui",
    "ShortCut": "Ui",
    "HSlider": "Ui",
    "Popup": "Ui",
    "VSlider": "Ui",
    "LinkButton": "Ui",
    "TextureRect": "Ui",
    "Panel": "Ui",
    "ToolButton": "Ui",
    "CheckButton": "Ui",
    "MenuButton": "Ui",
    "PopupPanel": "Ui",
    "CheckBox": "Ui",
    "NinePatchRect": "Ui",
    "Container": "Ui",
    "ColorRect": "Ui",
    "GrooveJoint2D": "Physics",
    "DampedSpringJoint2D": "Physics",
    "TileSet": "Graphics",
    "PinJoint2D": "Physics",
    "Joint2D": "Physics",
    "TileMap": "Graphics",
    "TouchScreenButton": "Ui",
    "ParallaxBackground": "Graphics",
    "ParallaxLayer": "Graphics",
    "RemoteTransform2D": "Core",
    "ArrayMesh": "Core",
    "PrimitiveMesh": "Core",
    "CubeMesh": "Core",
    "CapsuleMesh": "Core",
    "CylinderMesh": "Core",
    "SphereMesh": "Core",
    "SpatialMaterial": "Graphics",
    "PlaneMesh": "Core",
    "QuadMesh": "Core",
    "PrismMesh": "Core",
    "Tabs": "Ui",
    "TabContainer": "Ui",
    "VSeparator": "Ui",
    "TextureButton": "Ui",
    "Separator": "Ui",
    "HSeparator": "Ui",
    "HBoxContainer": "Ui",
    "BitMap": "Core",
    "VBoxContainer": "Ui",
    "GridContainer": "Ui",
    "BoxContainer": "Ui",
    "PanelContainer": "Ui",
    "TextureProgress": "Ui",
    "CenterContainer": "Ui",
    "ScrollContainer": "Ui",
    "ItemList": "Ui",
    "LineEdit": "Ui",
    "ConfirmationDialog": "Ui",
    "WindowDialog": "Ui",
    "VideoStream": "Video",
    "AcceptDialog": "Ui",
    "FileDialog": "Ui",
    "VideoPlayer": "Ui",
    "PopupMenu": "Ui",
    "Tree": "Ui",
    "TextEdit": "Ui",
    "OptionButton": "Ui",
    "TreeItem": "Core",
    "HSplitContainer": "Ui",
    "MarginContainer": "Ui",
    "PopupDialog": "Ui",
    "SplitContainer": "Ui",
    "VSplitContainer": "Ui",
    "GraphNode": "Ui",
    "ViewportContainer": "Ui",
    "SpinBox": "Ui",
    "ReferenceRect": "Ui",
    "ColorPicker": "Ui",
    "ColorPickerButton": "Ui",
    "RichTextLabel": "Ui",
    "Skeleton": "Animation",
    "SpatialGizmo": "Core",
    "AnimationPlayer": "Animation",
    "GraphEdit": "Ui",
    "Spatial": "Core",
    "Camera": "Core",
    "Environment": "Core",
    "Listener": "Core",
    "ARVRController": "ArVr",
    "ARVRCamera": "ArVr",
    "SpriteBase3D": "Graphics",
    "MeshInstance": "Core",
    "InterpolatedCamera": "Core",
    "ImmediateGeometry": "Core",
    "Mesh": "Core",
    "ARVROrigin": "ArVr",
    "ARVRAnchor": "ArVr",
    "Sprite3D": "Graphics",
    "Tween": "Animation",
    "BoneAttachment": "Animation",
    "GeometryInstance": "Core",
    "VisualInstance": "Core",
    "AnimationTreePlayer": "Animation",
    "BakedLightmapData": "Graphics",
    "SpriteFrames": "Graphics",
    "Light": "Graphics",
    "AnimatedSprite3D": "Graphics",
    "DirectionalLight": "Graphics",
    "SpotLight": "Graphics",
    "ReflectionProbe": "Graphics",
    "OmniLight": "Graphics",
    "GIProbe": "Graphics",
    "BakedLightmap": "Graphics",
    "GIProbeData": "Graphics",
    "CollisionPolygon2D": "Physics",
    "RayCast2D": "Core",
    "VisibilityNotifier2D": "Core",
    "VisibilityEnabler2D": "Core",
    "KinematicBody2D": "Physics",
    "KinematicCollision2D": "Physics",
    "Area2D": "Physics",
    "Shape2D": "Core",
    "CollisionShape2D": "Physics",
    "YSort": "Core",
    "BackBufferCopy": "Core",
    "Camera2D": "Core",
    "Polygon2D": "Core",
    "OccluderPolygon2D": "Graphics",
    "LightOccluder2D": "Graphics",
    "Skeleton2D": "Animation",
    "Bone2D": "Animation",
    "Light2D": "Graphics",
    "Particles": "Graphics",
    "CPUParticles": "Graphics",
    "Curve": "Core",
    "GradientTexture": "Core",
    "Position3D": "Core",
    "NavigationMesh": "Core",
    "NavigationMeshInstance": "Core",
    "Navigation": "Core",
    "RootMotionView": "Core",
    "AnimationTree": "Animation",
    "AnimationNodeBlendTree": "Animation",
    "AnimationRootNode": "Animation",
    "AnimationNode": "Animation",
    "AnimationNodeBlendSpace1D": "Animation",
    "AnimationNodeBlendSpace2D": "Animation",
    "AnimationNodeStateMachine": "Animation",
    "AnimationNodeStateMachineTransition": "Animation",
    "AnimationNodeOneShot": "Animation",
    "AnimationNodeOutput": "Animation",
    "KinematicCollision": "Physics",
    "PhysicalBone": "Physics",
    "KinematicBody": "Physics",
    "SoftBody": "Physics",
    "VehicleBody": "Physics",
    "VehicleWheel": "Physics",
    "Area": "Physics",
    "ProximityGroup": "Core",
    "Shape": "Core",
    "Curve3D": "Core",
    "RayCast": "Core",
    "MultiMeshInstance": "Core",
    "CollisionShape": "Physics",
    "MultiMesh": "Core",
    "CollisionPolygon": "Core",
    "Path": "Core",
    "PathFollow": "Core",
    "RemoteTransform": "Core",
    "OrientedPathFollow": "Core",
    "WorldEnvironment": "Core",
    "VisibilityEnabler": "Core",
    "VisibilityNotifier": "Core",
    "AnimationNodeAdd2": "Animation",
    "AnimationNodeAdd3": "Animation",
    "AnimationNodeAnimation": "Animation",
    "AnimationNodeTimeSeek": "Animation",
    "AnimationNodeBlend3": "Animation",
    "AnimationNodeBlend2": "Animation",
    "AnimationNodeTimeScale": "Animation",
    "AnimationNodeTransition": "Animation",
    "PhysicsBody": "Physics",
    "CollisionObject": "Physics",
    "StaticBody": "Physics",
    "PhysicsMaterial": "Physics",
    "RigidBody": "Physics",
    "CurveTexture": "Graphics",
    "ParticlesMaterial": "Graphics",
    "MeshDataTool": "Core",
    "SurfaceTool": "Core",
    "CylinderShape": "Core",
    "ConvexPolygonShape": "Core",
    "PlaneShape": "Core",
    "CapsuleShape": "Core",
    "ConcavePolygonShape": "Core",
    "SpatialVelocityTracker": "Core",
    "RayShape": "Core",
    "SphereShape": "Core",
    "BoxShape": "Core",
    "Particles2D": "Graphics",
    "VisualShaderNodeColorUniform": "Graphics",
    "VisualShaderNodeCubeMapUniform": "Graphics",
    "ShaderMaterial": "Graphics",
    "VisualShaderNodeTransformUniform": "Graphics",
    "VisualShaderNodeVec3Uniform": "Graphics",
    "VisualShaderNodeTextureUniform": "Graphics",
    "Material": "Core",
    "CanvasItemMaterial": "Graphics",
    "Sprite": "Graphics",
    "Line2D": "Core",
    "Position2D": "Core",
    "AnimatedSprite": "Graphics",
    "MeshInstance2D": "Core",
    "CollisionObject2D": "Physics",
    "Gradient": "Core",
    "StaticBody2D": "Physics",
    "RigidBody2D": "Physics",
    "PhysicsBody2D": "Physics",
    "Joint": "Physics",
    "PinJoint": "Physics",
    "HingeJoint": "Physics",
    "SliderJoint": "Physics",
    "Generic6DOFJoint": "Physics",
    "ConeTwistJoint": "Physics",
    "VisualShader": "Graphics",
    "Shader": "Core",
    "MeshLibrary": "Core",
    "VisualShaderNodeInput": "Graphics",
    "VisualShaderNodeOutput": "Graphics",
    "VisualShaderNodeColorConstant": "Graphics",
    "VisualShaderNodeVec3Constant": "Graphics",
    "VisualShaderNodeTransformConstant": "Graphics",
    "VisualShaderNodeScalarConstant": "Graphics",
    "VisualShaderNodeScalarOp": "Graphics",
    "VisualShaderNode": "Graphics",
    "VisualShaderNodeVectorOp": "Graphics",
    "VisualShaderNodeColorOp": "Graphics",
    "VisualShaderNodeTransformMult": "Graphics",
    "VisualShaderNodeScalarFunc": "Graphics",
    "VisualShaderNodeVectorFunc": "Graphics",
    "VisualShaderNodeTransformVecMult": "Graphics",
    "VisualShaderNodeScalarInterp": "Graphics",
    "VisualShaderNodeTexture": "Graphics",
    "VisualShaderNodeVectorInterp": "Graphics",
    "VisualShaderNodeTransformDecompose": "Graphics",
    "VisualShaderNodeUniform": "Graphics",
    "VisualShaderNodeVectorDecompose": "Graphics",
    "VisualShaderNodeScalarUniform": "Graphics",
    "VisualShaderNodeDotProduct": "Graphics",
    "VisualShaderNodeVectorCompose": "Graphics",
    "VisualShaderNodeCubeMap": "Graphics",
    "CubeMap": "Graphics",
    "VisualShaderNodeVectorLen": "Graphics",
    "VisualShaderNodeTransformCompose": "Graphics",
    "PanoramaSky": "Core",
    "Sky": "Core",
    "StreamTexture": "Network",
    "ImageTexture": "Core",
    "LargeTexture": "Core",
    "AtlasTexture": "Core",
    "ProxyTexture": "Core",
    "AnimatedTexture": "Core",
    "ProceduralSky": "Core",
    "BitmapFont": "Core",
    "Font": "Core",
    "Animation": "Animation",
    "StyleBoxFlat": "Core",
    "StyleBoxLine": "Core",
    "AudioStreamPlayer": "Audio",
    "PolygonPathFinder": "Core",
    "AudioStreamPlayer2D": "Audio",
    "AudioStreamPlayer3D": "Audio",
    "TextFile": "Core",
    "DynamicFontData": "Core",
    "DynamicFont": "Core",
    "StyleBoxEmpty": "Core",
    "StyleBoxTexture": "Core",
    "StyleBox": "Core",
    "LineShape2D": "Core",
    "SegmentShape2D": "Core",
    "AudioStreamSample": "Audio",
    "RayShape2D": "Core",
    "Curve2D": "Core",
    "Path2D": "Core",
    "PathFollow2D": "Core",
    "RectangleShape2D": "Core",
    "CapsuleShape2D": "Core",
    "CircleShape2D": "Core",
    "ConvexPolygonShape2D": "Core",
    "ConcavePolygonShape2D": "Core",
    "NavigationPolygon": "Core",
    "NavigationPolygonInstance": "Core",
    "Navigation2D": "Core",
    "SceneState": "Core",
    "SceneTree": "Core",
    "PackedScene": "Core",
    "SceneTreeTimer": "Core",
    "CSGBox": "Graphics",
    "CSGCylinder": "Graphics",
    "CSGTorus": "Graphics",
    "CSGPolygon": "Graphics",
    "CSGCombiner": "Graphics",
    "NetworkedMultiplayerENet": "Network",
    "GDNativeLibrary": "Core",
    "PluginScript": "Core",
    "NativeScript": "Core",
    "GDScriptFunctionState": "Core",
    "GridMap": "Core",
    "StreamPeerGDNative": "Network",
    "GDNative": "Core",
    "PacketPeerGDNative": "Network",
    "MultiplayerPeerGDNative": "Network",
    "ARVRInterfaceGDNative": "ArVr",
    "GDScript": "Core",
    "RegExMatch": "Core",
    "RegEx": "Core",
    "EditorPlugin": "Editor",
    "EditorFileDialog": "Editor",
    "EditorScript": "Editor",
    "EditorSelection": "Editor",
    "EditorImportPlugin": "Editor",
    "EditorSpatialGizmo": "Editor",
    "EditorResourcePreviewGenerator": "Editor",
    "EditorFileSystem": "Editor",
    "EditorSettings": "Editor",
    "EditorResourcePreview": "Editor",
    "ScriptEditor": "Editor",
    "EditorFileSystemDirectory": "Editor",
    "EditorExportPlugin": "Editor",
    "EditorResourceConversionPlugin": "Editor",
    "EditorSceneImporter": "Editor",
    "EditorInterface": "Editor",
    "EditorInspectorPlugin": "Editor",
    "EditorProperty": "Editor",
    "EditorInspector": "Editor",
    "AnimationTrackEditPlugin": "Animation",
    "ScriptCreateDialog": "Editor",
    "CSGMesh": "Graphics",
    "CSGSphere": "Graphics",
    "EditorScenePostImport": "Editor",
    "CSGShape": "Graphics",
    "JavaScript": "Core",
    "CSGPrimitive": "Graphics",
    "ResourceImporterOGGVorbis": "Audio",
    "UPNP": "Network",
    "VideoStreamTheora": "Video",
    "AudioStreamOGGVorbis": "Audio",
    "ResourceImporter": "Core",
    "UPNPDevice": "Network",
    "VisualScript": "VisualScript",
    "VisualScriptNode": "VisualScript",
    "VisualScriptVariableGet": "VisualScript",
    "VisualScriptFunction": "VisualScript",
    "VisualScriptFunctionState": "VisualScript",
    "VisualScriptOperator": "VisualScript",
    "VisualScriptMathConstant": "VisualScript",
    "VisualScriptIndexGet": "VisualScript",
    "VisualScriptIndexSet": "VisualScript",
    "VisualScriptClassConstant": "VisualScript",
    "VisualScriptGlobalConstant": "VisualScript",
    "VisualScriptVariableSet": "VisualScript",
    "VisualScriptConstant": "VisualScript",
    "VisualScriptSubCall": "VisualScript",
    "VisualScriptConstructor": "VisualScript",
    "VisualScriptResourcePath": "VisualScript",
    "VisualScriptSceneNode": "VisualScript",
    "VisualScriptCustomNode": "VisualScript",
    "VisualScriptBasicTypeConstant": "VisualScript",
    "VisualScriptSceneTree": "VisualScript",
    "VisualScriptSelf": "VisualScript",
    "VisualScriptComment": "VisualScript",
    "VisualScriptEngineSingleton": "VisualScript",
    "VisualScriptFunctionCall": "VisualScript",
    "VisualScriptDeconstruct": "VisualScript",
    "VisualScriptInputAction": "VisualScript",
    "VisualScriptPreload": "VisualScript",
    "VisualScriptTypeCast": "VisualScript",
    "VisualScriptLocalVar": "VisualScript",
    "VisualScriptLocalVarSet": "VisualScript",
    "VisualScriptPropertySet": "VisualScript",
    "VisualScriptCondition": "VisualScript",
    "VisualScriptEmitSignal": "VisualScript",
    "VisualScriptIterator": "VisualScript",
    "VisualScriptPropertyGet": "VisualScript",
    "VisualScriptReturn": "VisualScript",
    "VisualScriptWhile": "VisualScript",
    "VisualScriptYield": "VisualScript",
    "VisualScriptSequence": "VisualScript",
    "VisualScriptSwitch": "VisualScript",
    "VisualScriptYieldSignal": "VisualScript",
    "VisualScriptBuiltinFunc": "VisualScript",
    "VisualScriptSelect": "VisualScript",
    "WebSocketServer": "Network",
    "WebSocketMultiplayerPeer": "Network",
    "WebSocketClient": "Network",
    "VisualScriptExpression": "VisualScript",
    "_VisualScriptEditor": "VisualScript",
    "VideoStreamWebm": "Video",
    "WebSocketPeer": "Network",
    "BulletPhysicsDirectBodyState": "Physics",
    "Physics2DServerSW": "Physics",
    "BulletPhysicsServer": "Physics",
    "Physics2DDirectBodyStateSW": "Physics",
    "_bindings_sentinel": "Unknown"
}
